CHANGES.rst
MANIFEST.in
Makefile
README.rst
setup.py
slaves.ini
tox.ini
examples/aws.ini
loads/__init__.py
loads/_patch.py
loads/case.py
loads/main.py
loads/measure.py
loads/util.py
loads/websockets.py
loads.egg-info/PKG-INFO
loads.egg-info/SOURCES.txt
loads.egg-info/dependency_links.txt
loads.egg-info/entry_points.txt
loads.egg-info/not-zip-safe
loads.egg-info/requires.txt
loads.egg-info/top_level.txt
loads/db/__init__.py
loads/db/_python.py
loads/db/_redis.py
loads/examples/__init__.py
loads/examples/echo_server.py
loads/examples/test_blog.py
loads/examples/test_demo.py
loads/observers/__init__.py
loads/observers/_irc.py
loads/output/__init__.py
loads/output/_file.py
loads/output/_funkload.py
loads/output/null.py
loads/output/std.py
loads/results/__init__.py
loads/results/_unittest.py
loads/results/adapter.py
loads/results/base.py
loads/results/remote.py
loads/results/zmqrelay.py
loads/runners/__init__.py
loads/runners/distributed.py
loads/runners/external.py
loads/runners/local.py
loads/tests/__init__.py
loads/tests/jobs.py
loads/tests/runner.py
loads/tests/ssh_server.py
loads/tests/support.py
loads/tests/test_brokerctrl.py
loads/tests/test_case.py
loads/tests/test_db.py
loads/tests/test_external_runner.py
loads/tests/test_full.py
loads/tests/test_functional.py
loads/tests/test_heartbeat.py
loads/tests/test_here.py
loads/tests/test_main.py
loads/tests/test_measure.py
loads/tests/test_message.py
loads/tests/test_observer_irc.py
loads/tests/test_output.py
loads/tests/test_python_db.py
loads/tests/test_redis_db.py
loads/tests/test_results_remote.py
loads/tests/test_results_zmqrelay.py
loads/tests/test_test_result.py
loads/tests/test_util.py
loads/tests/test_websockets.py
loads/transport/__init__.py
loads/transport/agent.py
loads/transport/broker.py
loads/transport/brokerctrl.py
loads/transport/client.py
loads/transport/exc.py
loads/transport/heartbeat.py
loads/transport/message.py
loads/transport/util.py