Metadata-Version: 1.0
Name: loads
Version: 0.2
Summary: A distributed load testing tool.
Home-page: https://github.com/mozilla-services/loads
Author: Mozilla Services
Author-email: services-dev@mozilla.org
License: APLv2.0
Platform: UNKNOWN
Classifier: Programming Language :: Python
